{
    "variable": [
        {
            "id": "baseUrl",
            "key": "baseUrl",
            "type": "string",
            "name": "string",
            "value": "http:\/\/localhost"
        }
    ],
    "info": {
        "name": "Laravel",
        "_postman_id": "3b0e4e1e-d9fb-46ee-8a4c-3d21da7dd25a",
        "description": "",
        "schema": "https:\/\/schema.getpostman.com\/json\/collection\/v2.1.0\/collection.json"
    },
    "item": [
        {
            "name": "Endpoints",
            "description": "",
            "item": [
                {
                    "name": "Send OTP",
                    "request": {
                        "url": {
                            "host": "{{baseUrl}}",
                            "path": "api\/v1\/sendOtp",
                            "query": [],
                            "raw": "{{baseUrl}}\/api\/v1\/sendOtp"
                        },
                        "method": "POST",
                        "header": [
                            {
                                "key": "Content-Type",
                                "value": "application\/json"
                            },
                            {
                                "key": "Accept",
                                "value": "application\/x-www-form-urlencoded"
                            }
                        ],
                        "body": {
                            "mode": "raw",
                            "raw": "{\"country_code\":\"60\",\"phone_no\":\"1234567890\"}"
                        },
                        "description": "Send SMS OTP to phone number",
                        "auth": {
                            "type": "noauth"
                        }
                    },
                    "response": [
                        {
                            "header": [],
                            "code": 200,
                            "body": "{\n \"message\": \"OTP Sent!\"\n}",
                            "name": "success"
                        },
                        {
                            "header": [],
                            "code": 422,
                            "body": "{\"errors\": [\"country_code\": [\"The Country COde field is required.\"], \"phone_no\": [\"The Phone No field is required.\"] ]}",
                            "name": "Invalid Form Fields"
                        }
                    ]
                },
                {
                    "name": "Verify OTP",
                    "request": {
                        "url": {
                            "host": "{{baseUrl}}",
                            "path": "api\/v1\/verifyOtp",
                            "query": [],
                            "raw": "{{baseUrl}}\/api\/v1\/verifyOtp"
                        },
                        "method": "POST",
                        "header": [
                            {
                                "key": "Content-Type",
                                "value": "application\/x-www-form-urlencoded"
                            },
                            {
                                "key": "Accept",
                                "value": "application\/json"
                            }
                        ],
                        "body": {
                            "mode": "urlencoded",
                            "urlencoded": [
                                {
                                    "key": "country_code",
                                    "value": "60",
                                    "type": "text",
                                    "description": "The country code of user's phone number."
                                },
                                {
                                    "key": "phone_no",
                                    "value": "1234567890",
                                    "type": "text",
                                    "description": "The Phone No of the user."
                                },
                                {
                                    "key": "otp",
                                    "value": "123456",
                                    "type": "text",
                                    "description": "The OTP sent to user's phone number."
                                }
                            ]
                        },
                        "description": "Login user into the system with OTP",
                        "auth": {
                            "type": "noauth"
                        }
                    },
                    "response": [
                        {
                            "header": [],
                            "code": 200,
                            "body": "{\n \"user\": {\n    id: 1,\n    name: \"John Smith\"\n },\n \"token\": \"AuthenticationTokenHere\"\n}",
                            "name": "success"
                        },
                        {
                            "header": [],
                            "code": 401,
                            "body": "{\"message\": \"Invalid login details\"}",
                            "name": "Invalid Login details"
                        },
                        {
                            "header": [],
                            "code": 422,
                            "body": "{\"errors\": [\"country_code\": [\"The Country COde field is required.\"], \"phone_no\": [\"The Phone No field is required.\"] ]}",
                            "name": "Invalid Form Fields"
                        }
                    ]
                },
                {
                    "name": "Login with Password",
                    "request": {
                        "url": {
                            "host": "{{baseUrl}}",
                            "path": "api\/v1\/loginWithPassword",
                            "query": [],
                            "raw": "{{baseUrl}}\/api\/v1\/loginWithPassword"
                        },
                        "method": "POST",
                        "header": [
                            {
                                "key": "Content-Type",
                                "value": "application\/json"
                            },
                            {
                                "key": "Accept",
                                "value": "application\/json"
                            },
                            {
                                "key": "Accept:",
                                "value": "application\/x-www-form-urlencoded"
                            }
                        ],
                        "body": {
                            "mode": "raw",
                            "raw": "{\"country_code\":\"60\",\"phone_no\":\"1234567890\",\"password\":\"abcd1234\"}"
                        },
                        "description": "",
                        "auth": {
                            "type": "noauth"
                        }
                    },
                    "response": [
                        {
                            "header": [],
                            "code": 200,
                            "body": "{\n \"user\": {},\n \"token\": \"auth_token\"\n}",
                            "name": "success"
                        },
                        {
                            "header": [],
                            "code": 401,
                            "body": "{\"message\": \"Invalid Credentials\"}",
                            "name": "Invalid Credentials"
                        },
                        {
                            "header": [],
                            "code": 422,
                            "body": "{\"errors\": [\"country_code\": [\"The Country COde field is required.\"], \"phone_no\": [\"The Phone No field is required.\"] ]}",
                            "name": "Invalid Form Fields"
                        }
                    ]
                },
                {
                    "name": "Register with OTP",
                    "request": {
                        "url": {
                            "host": "{{baseUrl}}",
                            "path": "api\/v1\/register\/otp",
                            "query": [],
                            "raw": "{{baseUrl}}\/api\/v1\/register\/otp"
                        },
                        "method": "POST",
                        "header": [
                            {
                                "key": "Content-Type",
                                "value": "application\/x-www-form-urlencoded"
                            },
                            {
                                "key": "Accept",
                                "value": "application\/json"
                            }
                        ],
                        "body": {
                            "mode": "urlencoded",
                            "urlencoded": [
                                {
                                    "key": "country_code",
                                    "value": "60",
                                    "type": "text",
                                    "description": "The country code of user's phone number."
                                },
                                {
                                    "key": "phone_no",
                                    "value": "1234567890",
                                    "type": "text",
                                    "description": "The Phone No of the user."
                                },
                                {
                                    "key": "otp",
                                    "value": "123456",
                                    "type": "text",
                                    "description": "The OTP sent to user's phone number."
                                },
                                {
                                    "key": "name",
                                    "value": "John Smith",
                                    "type": "text",
                                    "description": "The name of the use."
                                },
                                {
                                    "key": "password",
                                    "value": "abcd1234",
                                    "type": "text",
                                    "description": "The password of the user."
                                }
                            ]
                        },
                        "description": "Register user with OTP",
                        "auth": {
                            "type": "noauth"
                        }
                    },
                    "response": [
                        {
                            "header": [],
                            "code": 200,
                            "body": "{\n \"user\": {\n    id: 1,\n    name: \"John Smith\"\n },\n \"token\": \"AuthenticationTokenHere\"\n}",
                            "name": "success"
                        },
                        {
                            "header": [],
                            "code": 422,
                            "body": "{\"errors\": [\"country_code\": [\"The Country COde field is required.\"], \"phone_no\": [\"The Phone No field is required.\"] ]}",
                            "name": "Invalid Form Fields"
                        }
                    ]
                },
                {
                    "name": "Logout",
                    "request": {
                        "url": {
                            "host": "{{baseUrl}}",
                            "path": "api\/v1\/logout",
                            "query": [],
                            "raw": "{{baseUrl}}\/api\/v1\/logout"
                        },
                        "method": "POST",
                        "header": [
                            {
                                "key": "Content-Type",
                                "value": "application\/x-www-form-urlencoded"
                            },
                            {
                                "key": "Accept",
                                "value": "application\/json"
                            }
                        ],
                        "body": null,
                        "description": "Log User Out and destroy any active tokens of user",
                        "auth": {
                            "type": "noauth"
                        }
                    },
                    "response": [
                        {
                            "header": [],
                            "code": 200,
                            "body": "{\"message\" : \"Logged Out\"}",
                            "name": "success"
                        },
                        {
                            "header": [],
                            "code": 401,
                            "body": "{\"message\": \"Access Denied\"}",
                            "name": "Access Denied"
                        }
                    ]
                }
            ]
        }
    ],
    "auth": {
        "type": "noauth"
    }
}